wanikani_notifier/__init__.py
wanikani_notifier/__main__.py
wanikani_notifier/cli.py
wanikani_notifier/wanikani.py
wanikani_notifier/notifiers/__init__.py
wanikani_notifier/notifiers/console.py
wanikani_notifier/notifiers/notifier.py
wanikani_notifier/notifiers/pushover.py
wanikani_notifier/notifiers/pushsafer.py
wanikani_notifier-0.6.1.dist-info/AUTHORS.rst
wanikani_notifier-0.6.1.dist-info/LICENSE
wanikani_notifier-0.6.1.dist-info/METADATA
wanikani_notifier-0.6.1.dist-info/WHEEL
wanikani_notifier-0.6.1.dist-info/entry_points.txt
wanikani_notifier-0.6.1.dist-info/top_level.txt
wanikani_notifier-0.6.1.dist-info/RECORD
