Metadata-Version: 2.1
Name: wanikani-notifier
Version: 0.6.1
Summary: Notifies a WaniKani user for new reviews to do.
Home-page: https://github.com/laurent-radoux/wanikani_notifier
Author: Laurent Radoux
Author-email: radoux.laurent@gmail.com
License: MIT license
Keywords: wanikani_notifier
Platform: UNKNOWN
Classifier: Development Status :: 3 - Alpha
Classifier: Intended Audience :: Developers
Classifier: License :: OSI Approved :: MIT License
Classifier: Natural Language :: English
Classifier: Programming Language :: Python :: 3
Classifier: Programming Language :: Python :: 3.7
Classifier: Programming Language :: Python :: 3.8
Classifier: Programming Language :: Python :: 3.9
Requires-Python: >=3.7
License-File: LICENSE
License-File: AUTHORS.rst
Requires-Dist: setuptools (==57.4.0)
Requires-Dist: Click (==7.0)
Requires-Dist: urllib3 (==1.26.6)
Requires-Dist: wanikani-api (==0.5.1)
Requires-Dist: python-pushsafer (==1.0)
Requires-Dist: chump (==1.6.0)
Requires-Dist: pytz (==2021.1)
Requires-Dist: ujson (==5.1.0)
